mcpq/__init__.py
mcpq/_abc.py
mcpq/_base.py
mcpq/_server.py
mcpq/_types.py
mcpq/_util.py
mcpq/colors.py
mcpq/constants.py
mcpq/entity.py
mcpq/entitytype.py
mcpq/events.py
mcpq/exception.py
mcpq/language.py
mcpq/material.py
mcpq/minecraft.py
mcpq/player.py
mcpq/text.py
mcpq/vec3.py
mcpq/world.py
mcpq/_proto/__init__.py
mcpq/_proto/minecraft_pb2.py
mcpq/_proto/minecraft_pb2_grpc.py
mcpq/nbt/__init__.py
mcpq/nbt/_block.py
mcpq/nbt/_parser.py
mcpq/nbt/_parser_wrapper.py
mcpq/nbt/_snbt_and_component.py
mcpq/nbt/_types.py
mcpq/tools/__init__.py
mcpq/tools/chatcmd.py
mcpq/tools/imagequantizer.py
mcpq/tools/mcturtle.py
mcpq-2.0.1.dist-info/licenses/LICENSE
mcpq-2.0.1.dist-info/METADATA
mcpq-2.0.1.dist-info/WHEEL
mcpq-2.0.1.dist-info/top_level.txt
mcpq-2.0.1.dist-info/RECORD
