Metadata-Version: 2.4
Name: mcpq
Version: 2.0.1
Summary: Library for communicating with and controlling Minecraft servers via MCPQ plugin
Author-email: Felix Wallner <felix.wallner@protonmail.com>
License: LGPL-3.0-or-later
Project-URL: Documentation, https://mcpq.github.io/mcpq-python/
Project-URL: Homepage, https://github.com/mcpq/mcpq-python
Project-URL: Issues, https://github.com/mcpq/mcpq-python/issues
Classifier: Programming Language :: Python
Classifier: Programming Language :: Python :: 3
Classifier: Programming Language :: Python :: 3.10
Classifier: Programming Language :: Python :: 3.11
Classifier: Programming Language :: Python :: 3.12
Classifier: Programming Language :: Python :: 3.13
Classifier: License :: OSI Approved :: GNU Lesser General Public License v3 or later (LGPLv3+)
Classifier: Operating System :: OS Independent
Requires-Python: >=3.10
License-File: LICENSE
Requires-Dist: grpcio>=1.65.4
Requires-Dist: protobuf>=3.20
Provides-Extra: dev
Requires-Dist: black; extra == "dev"
Requires-Dist: build; extra == "dev"
Requires-Dist: grpcio-tools>=1.65.4; extra == "dev"
Requires-Dist: isort; extra == "dev"
Requires-Dist: lark; extra == "dev"
Requires-Dist: mypy; extra == "dev"
Requires-Dist: nox; extra == "dev"
Requires-Dist: pre-commit; extra == "dev"
Requires-Dist: pytest; extra == "dev"
Requires-Dist: pytest-integration; extra == "dev"
Requires-Dist: pytest-mock; extra == "dev"
Requires-Dist: pytest-timeout; extra == "dev"
Requires-Dist: types-protobuf; extra == "dev"
Requires-Dist: types-setuptools; extra == "dev"
Provides-Extra: docs
Requires-Dist: myst-parser; extra == "docs"
Requires-Dist: sphinx; extra == "docs"
Provides-Extra: tools
Requires-Dist: imageio; extra == "tools"
Requires-Dist: numpy; extra == "tools"
Requires-Dist: Pillow; extra == "tools"
Requires-Dist: scipy; extra == "tools"
Dynamic: license-file
